ivy_mech/__init__.py
ivy_mech/orientation/__init__.py
ivy_mech/orientation/axis_angle.py
ivy_mech/orientation/euler_angles.py
ivy_mech/orientation/quaternion.py
ivy_mech/orientation/rotation_matrix.py
ivy_mech/pose/__init__.py
ivy_mech/pose/axis_angle_pose.py
ivy_mech/pose/euler_pose.py
ivy_mech/pose/matrix_pose.py
ivy_mech/pose/quaternion_pose.py
ivy_mech/position/__init__.py
ivy_mech/position/coordinate_conversions.py
ivy_mech/position/transformations.py
ivy_mech-1.1.9.dist-info/LICENSE
ivy_mech-1.1.9.dist-info/METADATA
ivy_mech-1.1.9.dist-info/WHEEL
ivy_mech-1.1.9.dist-info/top_level.txt
ivy_mech-1.1.9.dist-info/RECORD
