Metadata-Version: 2.1
Name: ivy-mech
Version: 1.1.9
Summary: Mechanics functions with end-to-end support for machine learning developers, written in Ivy
Home-page: https://ivy-dl.org/mech
Author: Ivy Team
Author-email: ivydl.team@gmail.com
License: Apache 2.0
Project-URL: Docs, https://ivy-dl.org/mech/
Project-URL: Source, https://github.com/ivy-dl/mech
Platform: UNKNOWN
Classifier: License :: OSI Approved :: Apache Software License
License-File: LICENSE
Requires-Dist: ivy-core
